giteaclient/__init__.py
giteaclient/api_client.py
giteaclient/configuration.py
giteaclient/rest.py
giteaclient/api/__init__.py
giteaclient/api/admin_api.py
giteaclient/api/issue_api.py
giteaclient/api/miscellaneous_api.py
giteaclient/api/notification_api.py
giteaclient/api/organization_api.py
giteaclient/api/repository_api.py
giteaclient/api/settings_api.py
giteaclient/api/user_api.py
giteaclient/models/__init__.py
giteaclient/models/access_token.py
giteaclient/models/add_collaborator_option.py
giteaclient/models/add_time_option.py
giteaclient/models/annotated_tag.py
giteaclient/models/annotated_tag_object.py
giteaclient/models/api_error.py
giteaclient/models/attachment.py
giteaclient/models/branch.py
giteaclient/models/branch_protection.py
giteaclient/models/combined_status.py
giteaclient/models/comment.py
giteaclient/models/commit.py
giteaclient/models/commit_affected_files.py
giteaclient/models/commit_date_options.py
giteaclient/models/commit_meta.py
giteaclient/models/commit_status.py
giteaclient/models/commit_status_state.py
giteaclient/models/commit_user.py
giteaclient/models/contents_response.py
giteaclient/models/create_access_token_option.py
giteaclient/models/create_branch_protection_option.py
giteaclient/models/create_branch_repo_option.py
giteaclient/models/create_email_option.py
giteaclient/models/create_file_options.py
giteaclient/models/create_fork_option.py
giteaclient/models/create_gpg_key_option.py
giteaclient/models/create_hook_option.py
giteaclient/models/create_hook_option_config.py
giteaclient/models/create_issue_comment_option.py
giteaclient/models/create_issue_option.py
giteaclient/models/create_key_option.py
giteaclient/models/create_label_option.py
giteaclient/models/create_milestone_option.py
giteaclient/models/create_o_auth2_application_options.py
giteaclient/models/create_org_option.py
giteaclient/models/create_pull_request_option.py
giteaclient/models/create_pull_review_comment.py
giteaclient/models/create_pull_review_options.py
python_giteaclient-1.16.8.dist-info/LICENSE
python_giteaclient-1.16.8.dist-info/METADATA
python_giteaclient-1.16.8.dist-info/WHEEL
python_giteaclient-1.16.8.dist-info/top_level.txt
python_giteaclient-1.16.8.dist-info/RECORD
