Metadata-Version: 2.1
Name: python-giteaclient
Version: 1.16.8
Summary: Gitea API client for python.
Home-page: UNKNOWN
Author-email: 
License: UNKNOWN
Keywords: Swagger,Gitea API.
Platform: UNKNOWN
License-File: LICENSE
Requires-Dist: urllib3 (>=1.15)
Requires-Dist: six (>=1.10)
Requires-Dist: certifi
Requires-Dist: python-dateutil
